marearts_anpr/__init__.py
marearts_anpr/_version.py
marearts_anpr/cli.py
marearts_anpr/image_processor.cp39-win_amd64.pyd
marearts_anpr/license.cp39-win_amd64.pyd
marearts_anpr/marearts_anpr.py
marearts_anpr/marearts_anpr_d.cp39-win_amd64.pyd
marearts_anpr/marearts_anpr_d_v14.cp39-win_amd64.pyd
marearts_anpr/marearts_anpr_p.cp39-win_amd64.pyd
marearts_anpr/marearts_anpr_r.cp39-win_amd64.pyd
marearts_anpr/marearts_anpr_r_v14.cp39-win_amd64.pyd
marearts_anpr/secret.cp39-win_amd64.pyd
marearts_anpr/tokenizer.cp39-win_amd64.pyd
marearts_anpr/utils.cp39-win_amd64.pyd
marearts_anpr-3.7.6.dist-info/LICENSE
marearts_anpr-3.7.6.dist-info/METADATA
marearts_anpr-3.7.6.dist-info/WHEEL
marearts_anpr-3.7.6.dist-info/entry_points.txt
marearts_anpr-3.7.6.dist-info/top_level.txt
marearts_anpr-3.7.6.dist-info/RECORD
