Metadata-Version: 2.1
Name: marearts-anpr
Version: 3.7.6
Summary: MareArts ANPR (Automatic Number Plate Recognition) library
Home-page: https://www.marearts.com
Author: MareArts
Author-email: hello@marearts.com
License: UNKNOWN
Platform: UNKNOWN
Classifier: Programming Language :: Python :: 3.9
Classifier: Programming Language :: Python :: 3.10
Classifier: Programming Language :: Python :: 3.11
Classifier: Programming Language :: Python :: 3.12
Classifier: License :: Other/Proprietary License
Classifier: Operating System :: OS Independent
Requires-Python: <3.13,>=3.9
License-File: LICENSE
Requires-Dist: opencv-python>=4.5.0
Requires-Dist: requests>=2.25.0
Requires-Dist: imageio>=2.10.0
Requires-Dist: pillow>=8.0.0
Requires-Dist: onnxruntime>=1.15.0
Requires-Dist: PyYAML>=5.0.0
Requires-Dist: dotmap>=1.3.0
Requires-Dist: marearts-crystal>=2.0.0
Requires-Dist: tqdm>=4.0.0
Requires-Dist: numpy<2.0,>=1.23.0; python_version == "3.10"
Requires-Dist: numpy<2.0,>=1.23.0; python_version == "3.11"
Requires-Dist: numpy<2.0,>=1.21.6; python_version == "3.9"
Requires-Dist: numpy<2.0,>=1.26.0; python_version >= "3.12"
Provides-Extra: cuda
Requires-Dist: onnxruntime-gpu>=1.15.0; extra == "cuda"
Provides-Extra: directml
Requires-Dist: onnxruntime-directml>=1.15.0; platform_system == "Windows" and extra == "directml"
Provides-Extra: gpu
Requires-Dist: onnxruntime-gpu>=1.15.0; extra == "gpu"
Provides-Extra: tensorrt
Requires-Dist: tensorrt>=8.6.0; platform_system == "Linux" and extra == "tensorrt"
Requires-Dist: pycuda>=2022.1; platform_system == "Linux" and extra == "tensorrt"
Requires-Dist: nvidia-cuda-runtime-cu12; platform_system == "Linux" and extra == "tensorrt"
